LICENSE
README.md
setup.py
huckelpy/__init__.py
huckelpy/atomic_orbital.py
huckelpy/basis_set.yaml
huckelpy/file_io.py
huckelpy/overlap_integral.py
huckelpy/tools.py
huckelpy.egg-info/PKG-INFO
huckelpy.egg-info/SOURCES.txt
huckelpy.egg-info/dependency_links.txt
huckelpy.egg-info/requires.txt
huckelpy.egg-info/top_level.txt