Metadata-Version: 2.1
Name: huckelpy
Version: 0.2.3
Summary: Package to calculate the molecular orbitals with the extended huckel method
Author: Efrem Bernuz
Author-email: komuisan@gmail.com
License: UNKNOWN
Platform: UNKNOWN
License-File: LICENSE
